{
  "pathParameters": {
    "userId": "cognito-user-mcc"
  },
  "body": "{\"name\": \"Event Campaign\", \"description\": \"Campaign using event template\", \"templateId\": \"event-announcement\", \"templateVersion\": \"v1.0.0\", \"audienceSelection\": { \"type\": \"tag\", \"values\": [\"basic-members\"] }, \"recipients\": { \"type\": \"groups\", \"groupIds\": [\"basic-members\"] }, \"status\": \"draft\", \"metadata\": { \"subject\": \"Upcoming Event!\", \"fromName\": \"GoodBricks Team\", \"fromEmail\": \"noreply@goodbricks.org\" }}"
}
